{"body": [{"indent": 0, "text": ["Area Light"], "type": "title", "extent": [0, 15], "level": 0}, {"indent": 0, "type": "summary", "extent": [63, 140], "text": ["Simulates a light in the shape of a line, rectangle, disk, or sphere."]}, {"indent": 0, "type": "para", "extent": [140, 242], "text": ["This tool creates an ", {"text": ["Light object"], "fullpath": "/nodes/obj/hlight", "scheme": "Node", "type": "link", "value": "/nodes/obj/hlight"}, " and sets the\n", {"text": ["Light type"], "type": "ui"}, " parameter to \"Grid\"."]}, {"indent": 0, "type": "para", "extent": [242, 383], "text": ["You can change the area light shape by changing the ", {"text": ["Light type"], "type": "ui"}, " parameter. Use the ", {"text": ["Area size"], "type": "ui"}, " parameter to set the size of the light."]}, {"body": [{"body": [{"indent": 4, "type": "para", "extent": [389, 458], "text": ["Lights are distributed along the length of a straight\n    line."]}, {"indent": 4, "type": "para", "extent": [458, 493], "text": [{"text": "", "fullpath": "/images/line_type.jpg", "scheme": "Image", "type": "link", "value": "/images/line_type.jpg"}]}], "indent": 0, "text": ["Line"], "extent": [383, 389], "container": true, "type": "dt"}, {"body": [{"indent": 4, "type": "para", "extent": [499, 606], "text": ["Lights are distributed over the area of a plane. This is the default shape created by the area light."]}, {"indent": 4, "type": "para", "extent": [606, 641], "text": [{"text": "", "fullpath": "/images/grid_type.jpg", "scheme": "Image", "type": "link", "value": "/images/grid_type.jpg"}]}], "indent": 0, "text": ["Grid"], "extent": [493, 499], "container": true, "type": "dt"}, {"body": [{"indent": 4, "type": "para", "extent": [647, 700], "text": ["Lights are distributed over the area of a disk."]}, {"indent": 4, "type": "para", "extent": [700, 735], "text": [{"text": "", "fullpath": "/images/disc_type.jpg", "scheme": "Image", "type": "link", "value": "/images/disc_type.jpg"}]}], "indent": 0, "text": ["Disk"], "extent": [641, 647], "container": true, "type": "dt"}, {"body": [{"indent": 4, "type": "para", "extent": [743, 814], "text": ["Lights are distributed along the outside surface of a\n    sphere."]}, {"indent": 4, "type": "para", "extent": [814, 940], "text": ["You can put objects inside this shape for an overall soft shadow look that is similar to global illumination irradiance."]}, {"indent": 4, "type": "para", "extent": [940, 977], "text": [{"text": "", "fullpath": "/images/sphere_type.jpg", "scheme": "Image", "type": "link", "value": "/images/sphere_type.jpg"}]}], "indent": 0, "text": ["Sphere"], "extent": [735, 743], "container": true, "type": "dt"}], "container": true, "type": "dt_group"}, {"indent": 0, "type": "para", "extent": [977, 1009], "text": ["See ", {"text": ["lighting"], "fullpath": "/render/lights", "scheme": null, "type": "link", "value": "/render/lights"}, "."]}], "summary": ["Simulates a light in the shape of a line, rectangle, disk, or sphere."], "type": "root", "attrs": {"tags": "lightsandcameras", "icon": "OBJ/light_spot"}, "title": ["Area Light"]}